{"references":[{"paperId":"4db4f1af1b94fbd5defa0fa0010fdc449dd1e96c","externalIds":{"DBLP":"conf/cpaior/DeudonCLAR18","MAG":"2805798351","DOI":"10.1007/978-3-319-93031-2_12","CorpusId":47017706},"title":"Learning Heuristics for the TSP by Policy Gradient"},{"paperId":"6c037dd0c406228daf80056579d0d998159daa40","externalIds":{"ArXiv":"1803.09621","MAG":"2795112307","DBLP":"journals/corr/abs-1803-09621","CorpusId":4357662},"title":"Learning the Multiple Traveling Salesmen Problem with Permutation Invariant Pooling Networks"},{"paperId":"0366b6396610708a77540564050a90a761a28937","externalIds":{"MAG":"2949922211","ArXiv":"1802.04240","DBLP":"conf/nips/NazariOST18","CorpusId":46892983},"title":"Reinforcement Learning for Solving the Vehicle Routing Problem"},{"paperId":"e57591fe81687430d08b7939a9484c8373ae0f64","externalIds":{"DBLP":"journals/cor/KobeagaML18","MAG":"2750785333","DOI":"10.1016/j.cor.2017.09.003","CorpusId":2394709},"title":"An efficient evolutionary algorithm for the orienteering problem"},{"paperId":"0f450869083f8c285b62e5e8ce18af35068686a1","externalIds":{"MAG":"2784910652","CorpusId":57634432},"title":"An Extension of the Lin-Kernighan-Helsgaun TSP Solver for Constrained Traveling Salesman and Vehicle Routing Problems: Technical report"},{"paperId":"33998aff64ce51df8dee45989cdca4b6b1329ec4","externalIds":{"DBLP":"journals/corr/abs-1710-10903","ArXiv":"1710.10903","MAG":"2766453196","DOI":"10.17863/CAM.48429","CorpusId":3292002},"title":"Graph Attention Networks"},{"paperId":"b36a5bb1707bb9c70025294b3a310138aae8327a","externalIds":{"MAG":"2899771611","CorpusId":40027675},"title":"Automatic differentiation in PyTorch"},{"paperId":"c27db32efa8137cbf654902f8f728f338e55cd1c","externalIds":{"MAG":"2766447205","DBLP":"journals/nature/SilverSSAHGHBLB17","DOI":"10.1038/nature24270","CorpusId":205261034,"PubMed":"29052630"},"title":"Mastering the game of Go without human knowledge"},{"paperId":"3e2742cbc683e2422e504f248ccf63f1a7983c69","externalIds":{"ArXiv":"1706.07450","DBLP":"journals/corr/NowakVBB17","MAG":"2647779349","CorpusId":22787957},"title":"A Note on Learning Algorithms for Quadratic Assignment with Graph Neural Networks"},{"paperId":"204e3073870fae3d05bcbc2f6a8e263d9b72e776","externalIds":{"DBLP":"journals/corr/VaswaniSPUJGKP17","MAG":"2963403868","ArXiv":"1706.03762","CorpusId":13756489},"title":"Attention is All you Need"},{"paperId":"1e819f533ef2bf5ca50a6b2008d96eaea2a2706e","externalIds":{"ArXiv":"1704.01665","DBLP":"journals/corr/DaiKZDS17","MAG":"2607264901","CorpusId":3486660},"title":"Learning Combinatorial Optimization Algorithms over Graphs"},{"paperId":"6c8353697cdbb98dfba4f493875778c4286d3e3a","externalIds":{"DBLP":"conf/cvpr/RennieMMRG17","MAG":"2963084599","ArXiv":"1612.00563","DOI":"10.1109/CVPR.2017.131","CorpusId":206594923},"title":"Self-Critical Sequence Training for Image Captioning"},{"paperId":"d7878c2044fb699e0ce0cad83e411824b1499dc8","externalIds":{"DBLP":"journals/corr/BelloPLNB16","ArXiv":"1611.09940","MAG":"2952332632","CorpusId":3649804},"title":"Neural Combinatorial Optimization with Reinforcement Learning"},{"paperId":"2ad76b5ea9cad4f9e5850f2451340452163d3864","externalIds":{"MAG":"2962990154","DBLP":"conf/fsttcs/EneNS17","ArXiv":"1610.01058","DOI":"10.4230/LIPIcs.FSTTCS.2017.27","CorpusId":3442219},"title":"Approximation Algorithms for Stochastic k-TSP"},{"paperId":"97fb4e3d45bb098e27e0071448b6152217bd35a5","externalIds":{"MAG":"3037932933","ArXiv":"1607.06450","DBLP":"journals/corr/BaKH16","CorpusId":8236317},"title":"Layer Normalization"},{"paperId":"9701a41de9ea609208b9ee13ddd0c07790576c79","externalIds":{"MAG":"2357843841","DBLP":"journals/computer/BalELNRSSW16","DOI":"10.1109/MC.2016.127","CorpusId":260780270},"title":"A Medium-Scale Distributed System for Computer Science Research: Infrastructure for the Long Term"},{"paperId":"2c03df8b48bf3fa39054345bafabfeff15bfd11d","externalIds":{"DBLP":"conf/cvpr/HeZRS16","MAG":"2949650786","ArXiv":"1512.03385","DOI":"10.1109/cvpr.2016.90","CorpusId":206594692},"title":"Deep Residual Learning for Image Recognition"},{"paperId":"d01379ebb53c66a4ccf5f4959d904dcf9e161e41","externalIds":{"MAG":"2951876403","DBLP":"journals/corr/VinyalsBK15","ArXiv":"1511.06391","CorpusId":260429228},"title":"Order Matters: Sequence to sequence for sets"},{"paperId":"9653d5c2c7844347343d073bbedd96e05d52f69b","externalIds":{"MAG":"3037280547","DBLP":"journals/corr/VinyalsFJ15","ArXiv":"1506.03134","CorpusId":5692837},"title":"Pointer Networks"},{"paperId":"0c908739fbff75f03469d13d4a1a07de3414ee19","externalIds":{"ArXiv":"1503.02531","MAG":"1821462560","DBLP":"journals/corr/HintonVD15","CorpusId":7200347},"title":"Distilling the Knowledge in a Neural Network"},{"paperId":"340f48901f72278f6bf78a04ee5b01df208cc508","externalIds":{"DBLP":"journals/nature/MnihKSRVBGRFOPB15","MAG":"2145339207","DOI":"10.1038/nature14236","CorpusId":205242740,"PubMed":"25719670"},"title":"Human-level control through deep reinforcement learning"},{"paperId":"995c5f5e62614fcb4d2796ad2faab969da51713e","externalIds":{"MAG":"1836465849","ArXiv":"1502.03167","DBLP":"conf/icml/IoffeS15","CorpusId":5808102},"title":"Batch Normalization: Accelerating Deep Network Training by Reducing Internal Covariate Shift"},{"paperId":"a6cb366736791bcccc5c8639de5a8f9636bf87e8","externalIds":{"MAG":"2964121744","DBLP":"journals/corr/KingmaB14","ArXiv":"1412.6980","CorpusId":6628106},"title":"Adam: A Method for Stochastic Optimization"},{"paperId":"189cd2973dceed7cd738fd4a5ef3d14da9ca16c3","externalIds":{"MAG":"2251882317","CorpusId":249430968},"title":"Vehicle Routing: Problems, Methods, and Applications, Second Edition"},{"paperId":"e003b48f6a8663f9ebbb91c45918046f9ab98265","externalIds":{"MAG":"2113873983","DBLP":"journals/eor/VansteenwegenSO11","DOI":"10.1016/j.ejor.2010.03.045","CorpusId":10893453},"title":"The orienteering problem: A survey"},{"paperId":"f418160139058493ae48576cc2a2b24aecce1a54","externalIds":{"MAG":"2140596151","DBLP":"journals/informs/FischettiGT98","DOI":"10.1287/ijoc.10.2.133","CorpusId":31866256},"title":"Solving the Orienteering Problem through Branch-and-Cut"},{"paperId":"8315dff3d304baf47c025f4b33535b9d693350c1","externalIds":{"MAG":"2151554678","DBLP":"journals/tec/DolpertM97","DOI":"10.1109/4235.585893","CorpusId":5553697},"title":"No free lunch theorems for optimization"},{"paperId":"b6ecc62a5745102605733181051ea10fecac5676","externalIds":{"MAG":"2171554447","DOI":"10.1287/MNSC.38.6.884","CorpusId":13802223},"title":"Some Guidelines and Guarantees for Common Random Numbers"},{"paperId":"d438ed1a6ab96c6039e8d9917e90cbf6d4815198","externalIds":{"DBLP":"journals/networks/Balas89","MAG":"1986056047","DOI":"10.1002/net.3230190602","CorpusId":206313434},"title":"The prize collecting traveling salesman problem"},{"paperId":"08bd46a1d89554868d496ec7ebae782d2af5f817","externalIds":{"MAG":"2003281104","DOI":"10.1002/1520-6750(198706)34:3<307::AID-NAV3220340302>3.0.CO;2-D","CorpusId":119849334},"title":"The Orienteering Problem"},{"paperId":"7a23da2c14f9355dd63a434b62cf5b28aeebc305","externalIds":{"MAG":"2585818457","DOI":"10.1007/BF00339943","CorpusId":36483354,"PubMed":"4027280"},"title":"“Neural” computation of decisions in optimization problems"},{"paperId":"7cbbccb182d4ba3c5de13625741bac44ec83d135","externalIds":{"MAG":"2014979043","DOI":"10.1057/JORS.1984.162","CorpusId":62711670},"title":"Heuristic Methods Applied to Orienteering"},{"paperId":"ac5e93895ab03bf47070dab04f62f58717442f0d","externalIds":{"DBLP":"conf/birthday/RosenkrantzSL13","MAG":"2956015669","DOI":"10.1137/0206041","CorpusId":14764079},"title":"An Analysis of Several Heuristics for the Traveling Salesman Problem"},{"paperId":"ed2098bfd3553887f388717cd41e285531944b2e","externalIds":{"MAG":"2503817654","CorpusId":124776816},"title":"Computers And Intractability A Guide To The Theory Of Np Completeness"},{"paperId":"4f8d648c52edf74e41b0996128aa536e13cc7e82","externalIds":{"DBLP":"journals/ijsc/HaoZM16","DOI":"10.1142/S1793351X16500045","CorpusId":1779661},"title":"Deep Learning"},{"paperId":"4c915c1eecb217c123a36dc6d3ce52d12c742614","externalIds":{"DOI":"10.1023/A:1022672621406","CorpusId":2332513},"title":"Simple Statistical Gradient-Following Algorithms for Connectionist Reinforcement Learning"},{"paperId":"5468769a0a040a3f31585233813e3fd94b5bf0b2","externalIds":{"MAG":"2117666205","DBLP":"journals/informs/Smith99","DOI":"10.1287/ijoc.11.1.15","CorpusId":5634955},"title":"Neural Networks for Combinatorial Optimization: A Review of More Than a Decade of Research"},{"paperId":"a8bc234360e1ff2a89bc84793d9528a70b1963f6","externalIds":{"CorpusId":271877547},"title":"An eﬃcient evolutionary algorithm for the orienteering problem"}]}